{
  "lastUpdated": "2026-02-07T22:54:41Z",
  "source": {
    "kind": "github-projects-public-html",
    "projectUrl": "https://github.com/users/luiscdano/projects/1",
    "projectTitle": "DevOps Workflow Board",
    "syncedAt": "2026-02-07T22:54:41Z"
  },
  "cards": [
    {
      "id": "issue-7",
      "title": "S5 · Preparar checklist y evidencia para 1er parcial",
      "week": "Sin semana",
      "status": "todo",
      "details": "Sincronizado automaticamente desde GitHub Projects (DevOps Workflow Board).",
      "proof": {
        "label": "Issue",
        "url": "https://github.com/luiscdano/DevOps.E2/issues/7"
      }
    },
    {
      "id": "issue-6",
      "title": "S4 · Configurar triggers CI sobre rama main",
      "week": "Sin semana",
      "status": "in-progress",
      "details": "Sincronizado automaticamente desde GitHub Projects (DevOps Workflow Board).",
      "proof": {
        "label": "Issue",
        "url": "https://github.com/luiscdano/DevOps.E2/issues/6"
      }
    },
    {
      "id": "issue-5",
      "title": "S4 · Crear programa Hola Mundo para CI",
      "week": "Sin semana",
      "status": "in-progress",
      "details": "Sincronizado automaticamente desde GitHub Projects (DevOps Workflow Board).",
      "proof": {
        "label": "Issue",
        "url": "https://github.com/luiscdano/DevOps.E2/issues/5"
      }
    },
    {
      "id": "issue-4",
      "title": "S4 · Workflow alerta.yml para ntfy.sh (en revision)",
      "week": "Sin semana",
      "status": "review-pr",
      "details": "Sincronizado automaticamente desde GitHub Projects (DevOps Workflow Board).",
      "proof": {
        "label": "Issue",
        "url": "https://github.com/luiscdano/DevOps.E2/issues/4"
      }
    },
    {
      "id": "issue-2",
      "title": "Document DevOps principles",
      "week": "Sin semana",
      "status": "done",
      "details": "Sincronizado automaticamente desde GitHub Projects (DevOps Workflow Board).",
      "proof": {
        "label": "Issue",
        "url": "https://github.com/luiscdano/DevOps.E2/issues/2"
      }
    },
    {
      "id": "issue-3",
      "title": "Setup repository workflow (dev → main)",
      "week": "Sin semana",
      "status": "done",
      "details": "Sincronizado automaticamente desde GitHub Projects (DevOps Workflow Board).",
      "proof": {
        "label": "Issue",
        "url": "https://github.com/luiscdano/DevOps.E2/issues/3"
      }
    }
  ],
  "movements": [
    {
      "date": "2026-02-07T22:38:00.399Z",
      "taskId": "issue-7",
      "from": "todo",
      "to": "todo",
      "note": "Tarea importada desde GitHub Projects"
    },
    {
      "date": "2026-02-07T22:38:00.399Z",
      "taskId": "issue-5",
      "from": "todo",
      "to": "in-progress",
      "note": "Tarea importada desde GitHub Projects"
    },
    {
      "date": "2026-02-07T22:38:00.399Z",
      "taskId": "issue-6",
      "from": "todo",
      "to": "in-progress",
      "note": "Tarea importada desde GitHub Projects"
    },
    {
      "date": "2026-02-07T22:38:00.399Z",
      "taskId": "issue-4",
      "from": "todo",
      "to": "review-pr",
      "note": "Tarea importada desde GitHub Projects"
    },
    {
      "date": "2026-02-07T22:38:00.399Z",
      "taskId": "issue-2",
      "from": "todo",
      "to": "done",
      "note": "Tarea importada desde GitHub Projects"
    },
    {
      "date": "2026-02-07T22:38:00.399Z",
      "taskId": "issue-3",
      "from": "todo",
      "to": "done",
      "note": "Tarea importada desde GitHub Projects"
    }
  ]
}
